LICENSE
MANIFEST.in
README.md
requirements.txt
setup.py
datadis/__init__.py
datadis/adaptors.py
datadis/validators.py
datadis/webservice.py
datadis/data/20codmun.csv
datadis/templates/autoconsumo.json
datadis/templates/codigos_error.error
datadis/templates/contrato.json
datadis/templates/maximaspotencia.json
datadis_aseme.egg-info/PKG-INFO
datadis_aseme.egg-info/SOURCES.txt
datadis_aseme.egg-info/dependency_links.txt
datadis_aseme.egg-info/requires.txt
datadis_aseme.egg-info/top_level.txt