Metadata-Version: 2.1
Name: datadis-aseme
Version: 1.3.4
Summary: Herramienta gestión API ASEME DATADIS
Home-page: https://github.com/gisce/datadis-aseme
Author: Francesc Puig
Author-email: devel@gisce.net
License: BSD 3-Clause License
Provides: datadis
License-File: LICENSE
